{
  "timestamp": "2025-11-28 09:32:19",
  "symbols": {
    "RELIANCE": {
      "strikes": {
        "1520": {
          "ema_ltp": 9.757061576843261,
          "cum_vwap_num": 373910.30000000005,
          "cum_vol": 35408,
          "iv": 17.59,
          "coi": 11
        },
        "1530": {
          "ema_ltp": 11.6991268157959,
          "cum_vwap_num": 380221.89999999997,
          "cum_vol": 29651,
          "iv": 17.3,
          "coi": 14
        },
        "1540": {
          "ema_ltp": 14.057630157470703,
          "cum_vwap_num": 779729.7500000001,
          "cum_vol": 50331,
          "iv": 16.89,
          "coi": 47
        },
        "1550": {
          "ema_ltp": 17.035400199890137,
          "cum_vwap_num": 1402792.4000000001,
          "cum_vol": 74927,
          "iv": 16.79,
          "coi": 129
        },
        "1560": {
          "ema_ltp": 20.630738258361816,
          "cum_vwap_num": 2275953.6500000004,
          "cum_vol": 100337,
          "iv": 16.73,
          "coi": 314
        },
        "1570": {
          "ema_ltp": 24.65526924133301,
          "cum_vwap_num": 1775770.1000000003,
          "cum_vol": 65703,
          "iv": 16.64,
          "coi": 184
        },
        "1580": {
          "ema_ltp": 29.097558975219727,
          "cum_vwap_num": 1182156.7500000002,
          "cum_vol": 37019,
          "iv": 16.65,
          "coi": 51
        },
        "1590": {
          "ema_ltp": 34.3455192565918,
          "cum_vwap_num": 428665.35000000003,
          "cum_vol": 11444,
          "iv": 16.67,
          "coi": 29
        },
        "1600": {
          "ema_ltp": 39.96866149902344,
          "cum_vwap_num": 898129.2999999999,
          "cum_vol": 20810,
          "iv": 16.89,
          "coi": -4
        },
        "1610": {
          "ema_ltp": 46.68449478149414,
          "cum_vwap_num": 67757.35,
          "cum_vol": 1377,
          "iv": 16.96,
          "coi": 24
        },
        "1620": {
          "ema_ltp": 54.737500000000004,
          "cum_vwap_num": 12742.1,
          "cum_vol": 226,
          "iv": 17.03,
          "coi": 3
        }
      },
      "meta": {
        "underlying": 1572.5
      }
    },
    "BHARTIARTL": {
      "strikes": {
        "2020": {
          "ema_ltp": 7.80625,
          "cum_vwap_num": 12639.8,
          "cum_vol": 1614,
          "iv": 17.75,
          "coi": -9
        },
        "2040": {
          "ema_ltp": 10.6875,
          "cum_vwap_num": 41410.899999999994,
          "cum_vol": 3859,
          "iv": 17.56,
          "coi": 7
        },
        "2060": {
          "ema_ltp": 14.806249999999999,
          "cum_vwap_num": 80010.45,
          "cum_vol": 5430,
          "iv": 17.39,
          "coi": 8
        },
        "2080": {
          "ema_ltp": 20.0,
          "cum_vwap_num": 110280.45,
          "cum_vol": 5531,
          "iv": 17.3,
          "coi": 59
        },
        "2100": {
          "ema_ltp": 26.68125,
          "cum_vwap_num": 414953.8,
          "cum_vol": 15640,
          "iv": 17.18,
          "coi": 1
        },
        "2120": {
          "ema_ltp": 34.975,
          "cum_vwap_num": 305823.25,
          "cum_vol": 8750,
          "iv": 17.24,
          "coi": 10
        },
        "2140": {
          "ema_ltp": 44.849999999999994,
          "cum_vwap_num": 245372.75,
          "cum_vol": 5471,
          "iv": 17.2,
          "coi": 31
        },
        "2160": {
          "ema_ltp": 56.28125,
          "cum_vwap_num": 113910.8,
          "cum_vol": 2026,
          "iv": 17.45,
          "coi": 12
        },
        "2180": {
          "ema_ltp": 69.04374999999999,
          "cum_vwap_num": 76970.25,
          "cum_vol": 1120,
          "iv": 17.82,
          "coi": 0
        },
        "2200": {
          "ema_ltp": 84.125,
          "cum_vwap_num": 33193.5,
          "cum_vol": 394,
          "iv": 18.1,
          "coi": 0
        },
        "2220": {
          "ema_ltp": 97.225,
          "cum_vwap_num": 3069.8,
          "cum_vol": 31,
          "iv": 16.75,
          "coi": 0
        }
      },
      "meta": {
        "underlying": 2116.9
      }
    },
    "HINDUNILVR": {
      "strikes": {
        "2360": {
          "ema_ltp": 3.0718750000000004,
          "cum_vwap_num": 44208.85,
          "cum_vol": 11850,
          "iv": 11.69,
          "coi": 22
        },
        "2380": {
          "ema_ltp": 4.3125,
          "cum_vwap_num": 77297.59999999999,
          "cum_vol": 14343,
          "iv": 10.97,
          "coi": 17
        },
        "2400": {
          "ema_ltp": 6.5,
          "cum_vwap_num": 133083.75,
          "cum_vol": 16359,
          "iv": 10.86,
          "coi": 66
        },
        "2420": {
          "ema_ltp": 10.134375,
          "cum_vwap_num": 163032.25,
          "cum_vol": 12838,
          "iv": 10.7,
          "coi": -31
        },
        "2440": {
          "ema_ltp": 15.796874999999998,
          "cum_vwap_num": 312315.24999999994,
          "cum_vol": 16049,
          "iv": 10.71,
          "coi": 160
        },
        "2460": {
          "ema_ltp": 24.5625,
          "cum_vwap_num": 310478.5,
          "cum_vol": 10680,
          "iv": 10.63,
          "coi": 168
        },
        "2480": {
          "ema_ltp": 36.6375,
          "cum_vwap_num": 198271.15,
          "cum_vol": 4686,
          "iv": 11.89,
          "coi": 102
        },
        "2500": {
          "ema_ltp": 50.853125,
          "cum_vwap_num": 180622.59999999998,
          "cum_vol": 3126,
          "iv": 12.55,
          "coi": -65
        },
        "2520": {
          "ema_ltp": 67.68124999999999,
          "cum_vwap_num": 46380.50000000001,
          "cum_vol": 600,
          "iv": 14.27,
          "coi": 7
        },
        "2540": {
          "ema_ltp": 39.05,
          "cum_vwap_num": 468.59999999999997,
          "cum_vol": 6,
          "iv": 15.71,
          "coi": 4
        },
        "2560": {
          "ema_ltp": 104.025,
          "cum_vwap_num": 2109.6,
          "cum_vol": 20,
          "iv": 17.51,
          "coi": 4
        }
      },
      "meta": {
        "underlying": 2463.7
      }
    },
    "SUNPHARMA": {
      "strikes": {
        "1700": {
          "ema_ltp": 3.5,
          "cum_vwap_num": 45.5,
          "cum_vol": 13,
          "iv": 17.59,
          "coi": 2
        },
        "1720": {
          "ema_ltp": 5.175000000000001,
          "cum_vwap_num": 1911.85,
          "cum_vol": 366,
          "iv": 17.17,
          "coi": 0
        },
        "1740": {
          "ema_ltp": 7.51875,
          "cum_vwap_num": 8397.4,
          "cum_vol": 1113,
          "iv": 16.67,
          "coi": 0
        },
        "1760": {
          "ema_ltp": 10.881250000000001,
          "cum_vwap_num": 9150.9,
          "cum_vol": 840,
          "iv": 16.31,
          "coi": 2
        },
        "1780": {
          "ema_ltp": 15.875,
          "cum_vwap_num": 23064.7,
          "cum_vol": 1451,
          "iv": 16.0,
          "coi": 4
        },
        "1800": {
          "ema_ltp": 22.625,
          "cum_vwap_num": 82231.09999999999,
          "cum_vol": 3624,
          "iv": 16.06,
          "coi": 14
        },
        "1820": {
          "ema_ltp": 31.65,
          "cum_vwap_num": 31770.55,
          "cum_vol": 1009,
          "iv": 16.09,
          "coi": 1
        },
        "1840": {
          "ema_ltp": 42.53125,
          "cum_vwap_num": 11082.300000000001,
          "cum_vol": 257,
          "iv": 16.22,
          "coi": -2
        },
        "1860": {
          "ema_ltp": 28.325,
          "cum_vwap_num": 3229.0499999999997,
          "cum_vol": 57,
          "iv": 0.0,
          "coi": 0
        },
        "1880": {
          "ema_ltp": 35.712500000000006,
          "cum_vwap_num": 7165.700000000001,
          "cum_vol": 100,
          "iv": 0.0,
          "coi": 0
        },
        "1900": {
          "ema_ltp": 43.89375,
          "cum_vwap_num": 17496.1,
          "cum_vol": 199,
          "iv": 0.0,
          "coi": 0
        }
      },
      "meta": {
        "underlying": 1810.0
      }
    },
    "WIPRO": {
      "strikes": {
        "237": {
          "ema_ltp": 1.51,
          "cum_vwap_num": 394.34,
          "cum_vol": 239,
          "iv": 20.0,
          "coi": 0
        },
        "240": {
          "ema_ltp": 1.8975,
          "cum_vwap_num": 3382.8000000000006,
          "cum_vol": 1772,
          "iv": 21.08,
          "coi": -7
        },
        "242": {
          "ema_ltp": 2.5012499999999998,
          "cum_vwap_num": 1003.95,
          "cum_vol": 397,
          "iv": 20.97,
          "coi": 12
        },
        "245": {
          "ema_ltp": 3.25,
          "cum_vwap_num": 9337.01,
          "cum_vol": 2846,
          "iv": 20.83,
          "coi": 53
        },
        "247": {
          "ema_ltp": 4.08875,
          "cum_vwap_num": 4728.93,
          "cum_vol": 1134,
          "iv": 21.0,
          "coi": 18
        },
        "250": {
          "ema_ltp": 5.23625,
          "cum_vwap_num": 19463.12,
          "cum_vol": 3680,
          "iv": 20.89,
          "coi": 51
        },
        "252": {
          "ema_ltp": 6.4312499999999995,
          "cum_vwap_num": 2993.1099999999997,
          "cum_vol": 455,
          "iv": 21.89,
          "coi": 6
        },
        "255": {
          "ema_ltp": 8.01375,
          "cum_vwap_num": 2743.2299999999996,
          "cum_vol": 340,
          "iv": 21.84,
          "coi": 0
        },
        "257": {
          "ema_ltp": 9.469999999999999,
          "cum_vwap_num": 228.64000000000001,
          "cum_vol": 23,
          "iv": 19.86,
          "coi": 1
        },
        "260": {
          "ema_ltp": 11.325,
          "cum_vwap_num": 5578.14,
          "cum_vol": 473,
          "iv": 21.07,
          "coi": -2
        },
        "262": {
          "ema_ltp": 0.0,
          "cum_vwap_num": 0.0,
          "cum_vol": 0,
          "iv": 0.0,
          "coi": 0
        }
      },
      "meta": {
        "underlying": 249.66
      }
    },
    "NIFTY": {
      "meta": {
        "underlying": 26229.4
      }
    },
    "BANKNIFTY": {
      "meta": {
        "underlying": 59679.55
      }
    },
    "TCS": {
      "meta": {
        "underlying": 3133.0
      }
    },
    "INFY": {
      "meta": {
        "underlying": 1562.2
      }
    },
    "HDFCBANK": {
      "meta": {
        "underlying": 1007.5
      }
    },
    "ICICIBANK": {
      "meta": {
        "underlying": 1393.2
      }
    },
    "KOTAKBANK": {
      "meta": {
        "underlying": 2106.7
      }
    },
    "ITC": {
      "meta": {
        "underlying": 403.25
      }
    },
    "SBIN": {
      "meta": {
        "underlying": 975.25
      }
    },
    "LT": {
      "meta": {
        "underlying": 4082.6
      }
    },
    "AXISBANK": {
      "meta": {
        "underlying": 1282.8
      }
    },
    "MARUTI": {
      "meta": {
        "underlying": 15935.0
      }
    },
    "BAJFINANCE": {
      "meta": {
        "underlying": 1035.6
      }
    },
    "ADANIENT": {
      "meta": {
        "underlying": 2260.1
      }
    },
    "ULTRACEMCO": {
      "meta": {
        "underlying": 11618.0
      }
    }
  }
}